{
  "Sign In": "Ingresar a mi cuenta",
  "Sign Up": "Crear Cuenta",
  "Sign in with your phone number": "Ingresar con mi numero telefonico",
  "Your phone number": "Numero Telefonico",
  "Your password": "Clave",
  "Forgot Password?": "Olvide mi clave",
  "Your name": "Nombre",
  "Your last name": "Apellido",
  "Create password": "Crear Clave",
  "Confirm password": "Confirmar Clave",
  "Agree to": "De acuerdo con ",
  "Terms & Conditions,": "Términos y condiciones, ",
  "Forgot Password": "Olvide mi clave",
  "SEND CODE TO PHONE": "ENVIAR CODIGO A MI TELEFONO",
  "Enter Code": "Ingresar Codigo",
  "Input received code": "Ingresar el codigo recibido",
  "SUBMIT": "ENVIAR",
  "Set New Password": "Establecer nueva clave",
  "Create new password": "Crear nueva clave",
  "Confirm new password": "Confirmar nueva clave",
  "CANCEL": "CANCELAR",
  "Terms & Conditions": "Terminos y Condiciones",
  "Privacy Policy": "Politica de privacidad",
  "Create Profile": "Crear Perfil",
  "Upload photo": "Subir Foto",
  "Full name": "Nombre Completo",
  "Email (optional)": "Correo",
  "Shipping address": "Direccion de Envio",
  "City": "Ciudad",
  "Zip Code": "Codigo Postal",
  "State": "Estado",
  "Country (MEX)": "Pais (MEX)",
  "Address name": "Direccion",
  "House number": "Numero Exterior",
  "City, ZIP": "Ciudad, Codigo postal",
  "Phone number": "Numero Telefonico",
  "Categories": "Categorias",
  "Orders": "GENERAL",
  "HALF PACKS": "CORRIDAS",
  "Reserved HP": "Reservado HP",
  "Reserved G":"Reservado G",
  "INVENTORY": "EXISTENCIAS",
  "Style": "Estilo",
  "price per piece": "Precio por pieza",
  "Half pack": "Corrida",
  "January": "Enero",
  "February": "Febrero",
  "March": "Marzo",
  "April": "Abril",
  "May": "Mayo",
  "June": "Junio",
  "July": "Julio",
  "August": "Agosto",
  "September": "Septiembre",
  "October": "Octubre",
  "November": "Noviembre",
  "December": "Diciembre",
  "Su": "Do",
  "Mo": "Lu",
  "Tu": "Ma",
  "We": "Mi",
  "Th": "Ju",
  "Fr": "Vi",
  "Sa": "Sa",
  "APPLY": "APLICAR",
  "Catalog order": "Ordenes de Catalogo",
  "Quantity": "Cantidad",
  "order half a pack (1S, 1M, 1L) or a full pack (2S,2M,2L), or combine": "Corrida (1S, 1M, 1L) o Paquete (2S,2M,2L)",
  "MOVE ITEMS TO CART": "AGREGAR A CARRITO",
  "Cart": "Carrito",
  "Style name": "Nombre de Estilo",
  "Total": "Total",
  "Remove": "Remover",
  "BUY": "COMPRAR",
  "RESERVE":"Reservar",
  "Category": "Categoria",
  "Settings": "Ajustes",
  "User name": "Nombre del usuario",
  "Send Feedback": "Enviar Comentarios",
  "Log Out": "Cerrar Sesion",
  "Are you sure?": "Esta Seguro?",
  "Yes": "Si",
  "No": "No",
  "Email address": "Correo Electronico",
  "Message": "Mensaje",
  "Admin Sign In": "Admin ingresar a cuenta",
  "Your email number": "Tu número de correo electrónico",
  "Your email": "Tu correo electrónico",
  "All Users": "Todos los Usuarios",
  "Search users": "Buscar Usuarios",
  "Push Notifications": "Notificacion",
  "CREATE NEW NOTIFICATION": "CREAR NUEVA NOTIFICACION",
  "All Notifications": "Todas las Notificaciones",
  "Create Push Notification": "Crear Notificacion",
  "Notification name": "Nombre de Notificacion",
  "Notification Text": "Mensaje de Notificacion",
  "CREATE NOTIFICATION": "CREAR NOTIFICACION",
  "Feedback": "Comentarios",
  "SEND": "ENVIAR",
  "Description": "Descripcion",
  "Price": "Precio",
  "Color": "Color",
  "Size": "Talla",
  "Brand": "Marca",
  "Save": "Guardar",
  "Product": "Producto",
  "Colors": "Colores",
  "Confirmed": "Confirmado",
  "Seller": "Vendedor",
  "Address": "Direccion",
  "Phone": "Numero de telefono",
  "Customer": "Cliente:",
  "Shipping Address": "Direccion de Envio",
  "Product:": "Producto:",
  "Packs": "Paquetes",
  "order Qty": "Cantidad",
  "Total Amount": "Total",
  "Subtotal": "Sub Total",
  "Shipping Cost": "Costo de Envio",
  "Discount": "Descuento",
  "Tracking Link": "Link del numero de guia",
  "Packing Video": "Video",
  "Submit the Invoice": "Enviar Factura",
  "Edit Invoice": "Editar Factura",
  "Send PDF Link to SMS": "Enviar PDF links a SMS",
  "LIST OF ALL USERS": "LISTA DE TODOS LOS USUARIOS",
  "total price": "precio total",
  "No List": "Sin lista",
  "History": "Historia",
  "Inventory": "EXISTENCIAS",
  "order": "ordenar",
  "Date": "Fecha",
  "Invoice": "Factura",
  "Email": "Correo electrónico",
  "Total Quantity": "Cantidad total",
  "Half Pack": "Medio Paquete",
  "Active": "Activo",
  "INVOICES": "FACTURAS",
  "Invoices": "Facturas",
  "Logout": "Cerrar sesión",
  "Error": "Error",
  "Cancel": "Cancelar",
  "Update": "Actualizar",
  "Pending": "Pendiente",
  "Completed": "Terminada",
  "User": "Usuaria",
  "Edit": "Editar",
  "Name": "Nombre",
  "Delete": "Borrar",
  "Update Invoice": "Actualizar factura",
  "Price Per Pack": "Precio por paquete",
  "Product update successfully!": "¡Actualización del producto con éxito!",
  "Photos Change Successfully": "Las fotos cambian con éxito",
  "Product has been deleted!": "¡El producto ha sido eliminado!",
  "Photos Add Successfully": "Fotos agregadas con éxito",
  "Product create successfully!": "¡Producto creado con éxito!",
  "You already picked this color please pick different color!": "Ya elegiste este color, ¡elige otro color!",
  "Profile Add Successfully": "Agregar perfil con éxito",
  "Your profile has been updated!": "¡Tu perfil ha sido actualizado!",
  "Shipping address (optional)": "Dirección de envío (opcional)",
  "Brands": "Marcas",
  "REMOVE FILTER": "QUITAR FILTRO",
  "Your item has moved to the cart!": "¡Tu artículo se ha movido al carrito!",
  "Invoice has been generated!": "¡Se ha generado la factura!",
  "Update Order": "Orden de actualización",
  "Process ORDERS": "Procesar PEDIDOS",
  "Process Orders": "Procesar pedidos",
  "Complete Order": "Procesar pedidos",
  "Customers": "Clientes",
  "Total Packs": "Total Packs",
  "Total order Qty": "Cantidad total del pedido",
  "CONFIRM ORDERS": "CONFIRMAR PEDIDOS",
  "Generate Invoice": "Generar Factura",
  "Order has been processed!": "¡El pedido ha sido procesado!",
  "Invoice has been submitted!": "¡Se ha enviado la factura!",
  "Create Push Notifications": "Crear notificaciones automáticas",
  "Notification successfully created!": "¡Notificación creada con éxito!",
  "Notification Content": "Contenido de la notificación",
  "Order has been confirmed!": "¡Se ha confirmado el pedido!",
  "Order has been canceled!": "¡El pedido ha sido cancelado!",
  "Invoice has been sent!": "¡Se ha enviado la factura!",
  "Don't know how to open this URL:": "No sé cómo abrir esta URL:",
  "Video Added Successfully": "Vídeo añadido con éxito",
  "Login as Admin?": "¿Iniciar sesión como administrador?",
  "Password doesn't match": "La contraseña no coincide",
  "SIGN IN": "REGISTRARSE",
  "Password at least 6 characters": "Contraseña de al menos 6 caracteres",
  "Signup Successfully!": "¡Regístrese con éxito!",
  "Login Successfully!": "¡Inicia sesión con éxito!",
  "Resend OTP!": "¡Reenviar OTP!",
  "Haven’t received it?": "¿No lo has recibido?",
  "Setup new password!": "¡Configura una nueva contraseña!",
  "Something went wrong!": "¡Algo salió mal!",
  "Error: Invalid OTP!": "Error: OTP no válida!",
  "OTP has been sent to": "OTP ha sido enviada a",
  "Feedback successfully sent!": "Comentarios enviados con éxito!",
  "Thanks for the Review!": "¡Gracias por la revisión!",
  "Respond feedback successfully!": "¡Responda los comentarios con éxito!",
  "Product removed from the cart!": "¡Producto eliminado del carrito!",
  "Your order has been submitted!": "¡Tu pedido ha sido enviado!",
  "MANAGE LISTING": "GESTIONAR LISTADO",
  "PENDING & CONFIRMED ORDERS": "PEDIDOS PENDIENTES Y CONFIRMADOS",
  "UPLOAD CONTENT": "SUBIR CONTENIDO",
  "Processing": "Procesando",
  "Spanish": "English?",
  "Edit Profile": "Editar perfil",
  "ZIP": "CÓDIGO POSTAL",
  "Country": "País",
  "Select Option": "Seleccionar opción",
  "Open Camera": "Cámara abierta",
  "Open Gallery": "Abrir galería",
  "CONFIRM": "CONFIRMAR",
  "Invoice has been updated!": "¡La factura ha sido actualizada!",
  "Invalid zip code": "Código postal no válido",
  "Product ID": "identificación de producto",
  "Email is not valid": "El correo no es válido",
  "Cart is empty": "El carrito esta vacío",
  "Delete Account": "Borrar cuenta",
  "Your account has been deleted": "Tu cuenta ha sido eliminada",
  "Alert": "Alerta",
  "Ok": "OK",
  "You can now login.": "Ahora puedes iniciar tu sesion.",
  "Pending Half Packs": "Pendiente",
  "View Products": "Ver productos",
  "Product image has been deleted!": "¡La imagen del producto ha sido eliminada!",
  "Unmatched": "Sin par",
  "Min": "mínimo",
  "Max": "máx.",
  "Canceled": "Cancelado",
  "Reserve Modal Text":"Gracias por su compra, en breve uno de nuestros representantes se comunicará con usted para completar el proceso de su pedido.",
  "Approve Reservations":"Aprobar Reservacion",
  "Cancel Reservations":"Cancelar Reservacion",
  "Reservations have been approved":"Las reservas han sido aprobadas",
  "Reservations have been cancelled":"Las reservas han sido canceladas.",
  "Confirm Cancel":"Confirmar",
  "SETTINGS": "Adjustes",
  "SplashScreen": "Splash Screen",
  "VIEW": "Vista",
  "UPLOAD": "Subir",
  "Confirm Change": "Confirmar Cambio",
  "You can login now":"Ahora puedes iniciar tu sesion."
}
